{
  "timestamp": "2025-04-22_23-38-36",
  "num_rounds": 5,
  "min_fit_clients": 1,
  "min_evaluate_clients": 1,
  "authorized_clients_only": false,
  "version_prefix": "1.0",
  "contract_address": "0xDCE0129848310Cd307d8Dda4B8CaFCdc5F9c6Bde",
  "final_metrics": {
    "round": 5,
    "eval_loss": 11.95086669921875,
    "eval_metrics": {
      "ensemble_size": 2.0,
      "accuracy": 10.0,
      "loss": 11.950866222381592,
      "num_clients": 1,
      "total_clients": 1,
      "authorized_clients": 1,
      "unauthorized_clients": 0,
      "avg_accuracy": 10.0
    },
    "num_clients": 1,
    "timestamp": "2025-04-22T16:38:50.268051+00:00"
  }
}