{
  "details": {
    "contribution_count": 62,
    "total_score": 905,
    "is_authorized": true,
    "last_contribution_timestamp": 1745734867,
    "rewards_earned": 0,
    "rewards_claimed": false
  },
  "records": [
    {
      "round": 1,
      "accuracy": 15.0,
      "score": 15,
      "timestamp": 1745510847,
      "rewarded": false
    },
    {
      "round": 1,
      "accuracy": 15.0,
      "score": 15,
      "timestamp": 1745510847,
      "rewarded": false
    },
    {
      "round": 2,
      "accuracy": 20.0,
      "score": 20,
      "timestamp": 1745510849,
      "rewarded": false
    },
    {
      "round": 2,
      "accuracy": 20.0,
      "score": 20,
      "timestamp": 1745510849,
      "rewarded": false
    },
    {
      "round": 3,
      "accuracy": 15.0,
      "score": 15,
      "timestamp": 1745510850,
      "rewarded": false
    },
    {
      "round": 3,
      "accuracy": 15.0,
      "score": 15,
      "timestamp": 1745510850,
      "rewarded": false
    },
    {
      "round": 1,
      "accuracy": 20.0,
      "score": 20,
      "timestamp": 1745551651,
      "rewarded": false
    },
    {
      "round": 1,
      "accuracy": 20.0,
      "score": 20,
      "timestamp": 1745551651,
      "rewarded": false
    },
    {
      "round": 2,
      "accuracy": 20.0,
      "score": 20,
      "timestamp": 1745551653,
      "rewarded": false
    },
    {
      "round": 2,
      "accuracy": 20.0,
      "score": 20,
      "timestamp": 1745551653,
      "rewarded": false
    },
    {
      "round": 3,
      "accuracy": 20.0,
      "score": 20,
      "timestamp": 1745551654,
      "rewarded": false
    },
    {
      "round": 3,
      "accuracy": 20.0,
      "score": 20,
      "timestamp": 1745551655,
      "rewarded": false
    },
    {
      "round": 1,
      "accuracy": 10.0,
      "score": 10,
      "timestamp": 1745552197,
      "rewarded": false
    },
    {
      "round": 1,
      "accuracy": 10.0,
      "score": 10,
      "timestamp": 1745552197,
      "rewarded": false
    },
    {
      "round": 2,
      "accuracy": 10.0,
      "score": 10,
      "timestamp": 1745552198,
      "rewarded": false
    },
    {
      "round": 2,
      "accuracy": 10.0,
      "score": 10,
      "timestamp": 1745552198,
      "rewarded": false
    },
    {
      "round": 3,
      "accuracy": 10.0,
      "score": 10,
      "timestamp": 1745552200,
      "rewarded": false
    },
    {
      "round": 3,
      "accuracy": 10.0,
      "score": 10,
      "timestamp": 1745552200,
      "rewarded": false
    },
    {
      "round": 1,
      "accuracy": 10.0,
      "score": 10,
      "timestamp": 1745681409,
      "rewarded": false
    },
    {
      "round": 1,
      "accuracy": 10.0,
      "score": 10,
      "timestamp": 1745681410,
      "rewarded": false
    },
    {
      "round": 2,
      "accuracy": 10.0,
      "score": 10,
      "timestamp": 1745681411,
      "rewarded": false
    },
    {
      "round": 2,
      "accuracy": 10.0,
      "score": 10,
      "timestamp": 1745681411,
      "rewarded": false
    },
    {
      "round": 3,
      "accuracy": 10.0,
      "score": 10,
      "timestamp": 1745681412,
      "rewarded": false
    },
    {
      "round": 3,
      "accuracy": 10.0,
      "score": 10,
      "timestamp": 1745681412,
      "rewarded": false
    },
    {
      "round": 1,
      "accuracy": 5.0,
      "score": 5,
      "timestamp": 1745681790,
      "rewarded": false
    },
    {
      "round": 1,
      "accuracy": 5.0,
      "score": 5,
      "timestamp": 1745681791,
      "rewarded": false
    },
    {
      "round": 2,
      "accuracy": 5.0,
      "score": 5,
      "timestamp": 1745681792,
      "rewarded": false
    },
    {
      "round": 2,
      "accuracy": 5.0,
      "score": 5,
      "timestamp": 1745681792,
      "rewarded": false
    },
    {
      "round": 3,
      "accuracy": 5.0,
      "score": 5,
      "timestamp": 1745681793,
      "rewarded": false
    },
    {
      "round": 3,
      "accuracy": 5.0,
      "score": 5,
      "timestamp": 1745681793,
      "rewarded": false
    },
    {
      "round": 1,
      "accuracy": 15.0,
      "score": 15,
      "timestamp": 1745730793,
      "rewarded": false
    },
    {
      "round": 1,
      "accuracy": 30.0,
      "score": 30,
      "timestamp": 1745731019,
      "rewarded": false
    },
    {
      "round": 1,
      "accuracy": 25.0,
      "score": 25,
      "timestamp": 1745731076,
      "rewarded": false
    },
    {
      "round": 1,
      "accuracy": 25.0,
      "score": 25,
      "timestamp": 1745731076,
      "rewarded": false
    },
    {
      "round": 2,
      "accuracy": 25.0,
      "score": 25,
      "timestamp": 1745731078,
      "rewarded": false
    },
    {
      "round": 2,
      "accuracy": 25.0,
      "score": 25,
      "timestamp": 1745731078,
      "rewarded": false
    },
    {
      "round": 3,
      "accuracy": 35.0,
      "score": 35,
      "timestamp": 1745731080,
      "rewarded": false
    },
    {
      "round": 3,
      "accuracy": 35.0,
      "score": 35,
      "timestamp": 1745731081,
      "rewarded": false
    },
    {
      "round": 1,
      "accuracy": 20.0,
      "score": 20,
      "timestamp": 1745732059,
      "rewarded": false
    },
    {
      "round": 1,
      "accuracy": 20.0,
      "score": 20,
      "timestamp": 1745732059,
      "rewarded": false
    },
    {
      "round": 2,
      "accuracy": 15.0,
      "score": 15,
      "timestamp": 1745732061,
      "rewarded": false
    },
    {
      "round": 2,
      "accuracy": 15.0,
      "score": 15,
      "timestamp": 1745732061,
      "rewarded": false
    },
    {
      "round": 3,
      "accuracy": 25.0,
      "score": 25,
      "timestamp": 1745732063,
      "rewarded": false
    },
    {
      "round": 3,
      "accuracy": 25.0,
      "score": 25,
      "timestamp": 1745732063,
      "rewarded": false
    },
    {
      "round": 1,
      "accuracy": 5.0,
      "score": 5,
      "timestamp": 1745732288,
      "rewarded": false
    },
    {
      "round": 1,
      "accuracy": 5.0,
      "score": 5,
      "timestamp": 1745732288,
      "rewarded": false
    },
    {
      "round": 2,
      "accuracy": 5.0,
      "score": 5,
      "timestamp": 1745732290,
      "rewarded": false
    },
    {
      "round": 2,
      "accuracy": 5.0,
      "score": 5,
      "timestamp": 1745732290,
      "rewarded": false
    },
    {
      "round": 3,
      "accuracy": 5.0,
      "score": 5,
      "timestamp": 1745732292,
      "rewarded": false
    },
    {
      "round": 3,
      "accuracy": 5.0,
      "score": 5,
      "timestamp": 1745732292,
      "rewarded": false
    },
    {
      "round": 1,
      "accuracy": 20.0,
      "score": 20,
      "timestamp": 1745733913,
      "rewarded": false
    },
    {
      "round": 1,
      "accuracy": 20.0,
      "score": 20,
      "timestamp": 1745733915,
      "rewarded": false
    },
    {
      "round": 2,
      "accuracy": 20.0,
      "score": 20,
      "timestamp": 1745733918,
      "rewarded": false
    },
    {
      "round": 2,
      "accuracy": 20.0,
      "score": 20,
      "timestamp": 1745733920,
      "rewarded": false
    },
    {
      "round": 3,
      "accuracy": 20.0,
      "score": 20,
      "timestamp": 1745733923,
      "rewarded": false
    },
    {
      "round": 3,
      "accuracy": 20.0,
      "score": 20,
      "timestamp": 1745733925,
      "rewarded": false
    },
    {
      "round": 1,
      "accuracy": 15.0,
      "score": 15,
      "timestamp": 1745734859,
      "rewarded": false
    },
    {
      "round": 1,
      "accuracy": 15.0,
      "score": 15,
      "timestamp": 1745734859,
      "rewarded": false
    },
    {
      "round": 2,
      "accuracy": 5.0,
      "score": 5,
      "timestamp": 1745734864,
      "rewarded": false
    },
    {
      "round": 2,
      "accuracy": 5.0,
      "score": 5,
      "timestamp": 1745734864,
      "rewarded": false
    },
    {
      "round": 3,
      "accuracy": 5.0,
      "score": 5,
      "timestamp": 1745734866,
      "rewarded": false
    },
    {
      "round": 3,
      "accuracy": 5.0,
      "score": 5,
      "timestamp": 1745734867,
      "rewarded": false
    }
  ]
}