{
  "timestamp": "2025-04-24_22-31-47",
  "num_rounds": 3,
  "min_fit_clients": 1,
  "min_evaluate_clients": 1,
  "authorized_clients_only": false,
  "version_prefix": "1.0",
  "contract_address": "0xDCE0129848310Cd307d8Dda4B8CaFCdc5F9c6Bde",
  "final_metrics": {
    "round": 3,
    "eval_loss": 21.682226181030273,
    "eval_metrics": {
      "ensemble_size": 4.0,
      "accuracy": 10.0,
      "loss": 21.68222665786743,
      "num_clients": 1,
      "total_clients": 1,
      "authorized_clients": 1,
      "unauthorized_clients": 0,
      "avg_accuracy": 10.0
    },
    "num_clients": 1,
    "timestamp": "2025-04-24T15:31:56.437937+00:00"
  }
}